satnogs_decoders-1.113.1.dist-info/licenses/LICENSE
satnogsdecoders/__init__.py
satnogsdecoders/_version.py
satnogsdecoders/decode_frame.py
satnogsdecoders/decode_multiple.py
satnogsdecoders/decoder/__init__.py
satnogsdecoders/decoder/aausat4.py
satnogsdecoders/decoder/acrux1.py
satnogsdecoders/decoder/aepex.py
satnogsdecoders/decoder/aisat.py
satnogsdecoders/decoder/alsat1n.py
satnogsdecoders/decoder/amicalsat.py
satnogsdecoders/decoder/amusat.py
satnogsdecoders/decoder/armadillo.py
satnogsdecoders/decoder/ascii85test.py
satnogsdecoders/decoder/astrocast.py
satnogsdecoders/decoder/asuphoenix.py
satnogsdecoders/decoder/ax25frames.py
satnogsdecoders/decoder/ax25monitor.py
satnogsdecoders/decoder/azaadisat2.py
satnogsdecoders/decoder/bdsat.py
satnogsdecoders/decoder/bdsat2.py
satnogsdecoders/decoder/beesat.py
satnogsdecoders/decoder/beesat2.py
satnogsdecoders/decoder/bisonsat.py
satnogsdecoders/decoder/bobcat1.py
satnogsdecoders/decoder/botan.py
satnogsdecoders/decoder/bugsat1.py
satnogsdecoders/decoder/cape1.py
satnogsdecoders/decoder/cas4.py
satnogsdecoders/decoder/cas5a.py
satnogsdecoders/decoder/cas9.py
satnogsdecoders/decoder/casaasat.py
satnogsdecoders/decoder/catsat.py
satnogsdecoders/decoder/celesta.py
satnogsdecoders/decoder/cevrosat.py
satnogsdecoders/decoder/chomptt.py
satnogsdecoders/decoder/cirbe.py
satnogsdecoders/decoder/co57.py
satnogsdecoders/decoder/co58.py
satnogsdecoders/decoder/co65.py
satnogsdecoders/decoder/co66.py
satnogsdecoders/decoder/connectat11.py
satnogsdecoders/decoder/cosmogirlsat.py
satnogsdecoders/decoder/crocube.py
satnogsdecoders/decoder/csim.py
satnogsdecoders/decoder/cspheader.py
satnogsdecoders/decoder/ctim.py
satnogsdecoders/decoder/cubebel1.py
satnogsdecoders/decoder/cubebel2.py
satnogsdecoders/decoder/cubesatsim.py
satnogsdecoders/decoder/cute.py
satnogsdecoders/decoder/delfin3xt.py
satnogsdecoders/decoder/delfipq.py
satnogsdecoders/decoder/dhabisat.py
satnogsdecoders/decoder/diy1.py
satnogsdecoders/decoder/dora.py
satnogsdecoders/decoder/dragonfly.py
satnogs_decoders-1.113.1.dist-info/METADATA
satnogs_decoders-1.113.1.dist-info/WHEEL
satnogs_decoders-1.113.1.dist-info/entry_points.txt
satnogs_decoders-1.113.1.dist-info/top_level.txt
satnogs_decoders-1.113.1.dist-info/RECORD
