Metadata-Version: 2.4
Name: satnogs-decoders
Version: 1.113.1
Summary: SatNOGS Decoders
Home-page: https://gitlab.com/librespacefoundation/satnogs/satnogs-decoders
Author: SatNOGS project
Author-email: dev@satnogs.org
License: AGPLv3
Classifier: Development Status :: 4 - Beta
Classifier: Environment :: Console
Classifier: Intended Audience :: Telecommunications Industry
Classifier: Intended Audience :: Science/Research
Classifier: License :: OSI Approved :: GNU Affero General Public License v3
Classifier: Operating System :: POSIX :: Linux
Classifier: Programming Language :: Python :: 3.6
Classifier: Topic :: Communications :: Ham Radio
License-File: LICENSE
Requires-Dist: kaitaistruct~=0.10.0
Requires-Dist: versioneer~=0.28.0
Provides-Extra: dev
Requires-Dist: build~=1.2.2; extra == "dev"
Requires-Dist: flake8-quotes~=3.4.0; extra == "dev"
Requires-Dist: flake8~=7.1.1; extra == "dev"
Requires-Dist: isort~=5.13.2; extra == "dev"
Requires-Dist: pylint~=3.3.3; extra == "dev"
Requires-Dist: pytest-forked~=1.6.0; extra == "dev"
Requires-Dist: pytest-xdist~=3.6.1; extra == "dev"
Requires-Dist: pytest~=8.3.4; extra == "dev"
Requires-Dist: tox~=4.24.1; extra == "dev"
Requires-Dist: yamllint~=1.15.0; extra == "dev"
Requires-Dist: yapf~=0.43.0; extra == "dev"
Requires-Dist: twine~=6.1.0; extra == "dev"
Dynamic: license-file
